oskut/__init__.py
oskut/extract_features.py
oskut/log_lib.py
oskut/preprocessing.py
oskut/deepcut/__init__.py
oskut/deepcut/deepcut.py
oskut/deepcut/model.py
oskut/deepcut/stop_words.py
oskut/deepcut/train.py
oskut/deepcut/utils.py
oskut/deepcut/weight/cnn_without_ne_ab.h5
oskut/deepcut/weight/cnn_without_ne_ab_tnhc.h5
oskut/model/ds_weights/lst20_rmsprop_LSTM_Attension_224_32_weight.h5
oskut/model/ds_weights/scads_rmsprop_LSTM_Attension_224_96_weight.h5
oskut/model/ds_weights/tnhc_rmsprop_LSTM_Attension_192_160_weight.h5
oskut/model/ds_weights/ws-augment-60p_rmsprop_LSTM_Attension_192_32_weight.h5
oskut/model/ds_weights/ws-newmm-augment-60p_rmsprop_LSTM_Attension_192_96_weight.h5
oskut/model/ds_weights/ws_rmsprop_LSTM_Attension_192_96_weight.h5
oskut/variable/words_modified.txt
oskut/weight/model_weight_best.h5
oskut/weight/model_weight_deepcut_tnhc.h5
oskut/weight/model_weight_lst20.h5
oskut/weight/model_weight_lst20_zeed0.h5
oskut/weight/model_weight_lst20_zeed42.h5
oskut/weight/model_weight_tnhc.h5
oskut/weight/model_weight_ws-augment-60p.h5
oskut/weight/model_weight_ws.h5
oskut/weight/ws_model_weight_best.h5
OSKut-1.3.dist-info/LICENSE
OSKut-1.3.dist-info/METADATA
OSKut-1.3.dist-info/WHEEL
OSKut-1.3.dist-info/top_level.txt
OSKut-1.3.dist-info/RECORD
