Metadata-Version: 2.1
Name: OSKut
Version: 1.3
Summary: Handling Cross- and Out-of-Domain Samples in Thai Word Segmentation (ACL 2020 Findings) Stacked Ensemble Framework and DeepCut as Baseline model
Home-page: https://github.com/mrpeerat/OSKut
Author: Peerat Limkonchotiwat
Author-email: peerat.limkonchotiwat@gmail.com
License: MIT
Keywords: thai,word segmentation,deep learning
Platform: UNKNOWN
Classifier: Development Status :: 5 - Production/Stable
Classifier: Programming Language :: Python :: 3
Classifier: Natural Language :: Thai
Classifier: Topic :: Scientific/Engineering :: Artificial Intelligence
Classifier: Topic :: Text Processing :: Linguistic
Requires-Dist: tensorflow (>=2.0.0)
Requires-Dist: pandas
Requires-Dist: scipy
Requires-Dist: numpy
Requires-Dist: scikit-learn
Requires-Dist: pyahocorasick (<=1.4.0)
